roll_the_dice/__init__.py
roll_the_dice/choice.py
roll_the_dice/dice.py
roll_the_dice/eight_ball.py
roll_the_dice/roll.py
plover_roll_the_dice-0.1.0.dist-info/METADATA
plover_roll_the_dice-0.1.0.dist-info/WHEEL
plover_roll_the_dice-0.1.0.dist-info/entry_points.txt
plover_roll_the_dice-0.1.0.dist-info/top_level.txt
plover_roll_the_dice-0.1.0.dist-info/zip-safe
plover_roll_the_dice-0.1.0.dist-info/RECORD
