Metadata-Version: 2.1
Name: plover-roll-the-dice
Version: 0.1.0
Summary: Plover text macros to roll dice, flip a coin, and take chances.
Home-page: https://github.com/morinted/plover_roll_the_dice
Author: Ted Morin
Author-email: morinted@gmail.com
License: GNU General Public License v3 or later (GPLv3+)
Keywords: plover plover_plugin
Platform: UNKNOWN
Classifier: Development Status :: 4 - Beta
Classifier: Environment :: Plugins
Classifier: Intended Audience :: End Users/Desktop
Classifier: License :: OSI Approved :: GNU General Public License v3 or later (GPLv3+)
Classifier: Operating System :: OS Independent
Classifier: Programming Language :: Python :: 3
Classifier: Programming Language :: Python :: 3.6
Classifier: Programming Language :: Python :: 3.7
Classifier: Programming Language :: Python :: 3.8
Classifier: Programming Language :: Python :: 3.9
Requires-Dist: plover (>=4.0.0.dev7)
